biobuddy/__init__.py
biobuddy/version.py
biobuddy/characteristics/__init__.py
biobuddy/characteristics/de_leva.py
biobuddy/characteristics/from_original_model.py
biobuddy/components/__init__.py
biobuddy/components/functions.py
biobuddy/components/model_utils.py
biobuddy/components/muscle_utils.py
biobuddy/components/segment_utils.py
biobuddy/components/via_point_utils.py
biobuddy/components/generic/__init__.py
biobuddy/components/generic/biomechanical_model.py
biobuddy/components/generic/muscle/__init__.py
biobuddy/components/generic/muscle/muscle.py
biobuddy/components/generic/muscle/muscle_group.py
biobuddy/components/generic/muscle/via_point.py
biobuddy/components/generic/rigidbody/__init__.py
biobuddy/components/generic/rigidbody/axis.py
biobuddy/components/generic/rigidbody/contact.py
biobuddy/components/generic/rigidbody/inertia_parameters.py
biobuddy/components/generic/rigidbody/marker.py
biobuddy/components/generic/rigidbody/mesh.py
biobuddy/components/generic/rigidbody/mesh_file.py
biobuddy/components/generic/rigidbody/range_of_motion.py
biobuddy/components/generic/rigidbody/segment.py
biobuddy/components/generic/rigidbody/segment_coordinate_system.py
biobuddy/components/real/__init__.py
biobuddy/components/real/biomechanical_model_real.py
biobuddy/components/real/model_dynamics.py
biobuddy/components/real/muscle/__init__.py
biobuddy/components/real/muscle/muscle_group_real.py
biobuddy/components/real/muscle/muscle_real.py
biobuddy/components/real/muscle/via_point_real.py
biobuddy/components/real/rigidbody/__init__.py
biobuddy/components/real/rigidbody/axis_real.py
biobuddy/components/real/rigidbody/contact_real.py
biobuddy/components/real/rigidbody/inertia_parameters_real.py
biobuddy/components/real/rigidbody/inertial_measurement_unit_real.py
biobuddy/components/real/rigidbody/marker_real.py
biobuddy/components/real/rigidbody/marker_weight.py
biobuddy/components/real/rigidbody/mesh_file_real.py
biobuddy/components/real/rigidbody/mesh_real.py
biobuddy-0.3.0.dist-info/licenses/LICENSE
biobuddy-0.3.0.dist-info/METADATA
biobuddy-0.3.0.dist-info/WHEEL
biobuddy-0.3.0.dist-info/top_level.txt
biobuddy-0.3.0.dist-info/RECORD
