Metadata-Version: 2.4
Name: biobuddy
Version: 0.3.0
Summary: A generic interface to generate a virtual buddy
Author-email: EveCharbie <eve.charbie@gmail.com>, Pariterre <pariterre@hotmail.com>
License: MIT
Project-URL: Documentation, https://github.com/pyomeca/biobuddy/tree/main#readme
Project-URL: Source, https://github.com/pyomeca/biobuddy
Project-URL: Tracker, https://github.com/pyomeca/biobuddy/issues
Classifier: License :: OSI Approved :: MIT License
Classifier: Programming Language :: Python
Requires-Python: >=3.11
License-File: LICENSE
Requires-Dist: numpy
Requires-Dist: ezc3d
Requires-Dist: lxml
Requires-Dist: scipy
Provides-Extra: test
Requires-Dist: pytest; extra == "test"
Requires-Dist: black; extra == "test"
Requires-Dist: opensim; extra == "test"
Requires-Dist: biorbd; extra == "test"
Requires-Dist: deepdiff; extra == "test"
Requires-Dist: pyorerun; extra == "test"
Requires-Dist: bioviz; extra == "test"
Requires-Dist: plotly; extra == "test"
Requires-Dist: pandas; extra == "test"
Dynamic: license-file
